nonebot_plugin_mcserver_status_check/__init__.py
nonebot_plugin_mcserver_status_check/checker.py
nonebot_plugin_mcserver_status_check/config.py
nonebot_plugin_mcserver_status_check/mc_renderer.py
nonebot_plugin_mcserver_status_check/minecraft.ttf
nonebot_plugin_mcserver_status_check-0.1.8.dist-info/licenses/LICENSE
nonebot_plugin_mcserver_status_check-0.1.8.dist-info/METADATA
nonebot_plugin_mcserver_status_check-0.1.8.dist-info/WHEEL
nonebot_plugin_mcserver_status_check-0.1.8.dist-info/RECORD
