Metadata-Version: 2.4
Name: nonebot-plugin-mcserver-status-check
Version: 0.1.8
Summary: A vanilla-style, beautiful and efficient Minecraft server status query plugin
License: MIT
License-File: LICENSE
Author: leiuary
Author-email: leiuary@qq.com
Requires-Python: >=3.9,<4.0
Classifier: License :: OSI Approved :: MIT License
Classifier: Programming Language :: Python :: 3
Classifier: Programming Language :: Python :: 3.9
Classifier: Programming Language :: Python :: 3.10
Classifier: Programming Language :: Python :: 3.11
Classifier: Programming Language :: Python :: 3.12
Classifier: Programming Language :: Python :: 3.13
Classifier: Programming Language :: Python :: 3.14
Requires-Dist: Pillow (>=9.1.0)
Requires-Dist: mcstatus (>=11.0.0)
Requires-Dist: nonebot-adapter-onebot (>=2.0.0,<3.0.0)
Requires-Dist: nonebot-plugin-alconna (>=0.30.0)
Requires-Dist: nonebot2 (>=2.3.0)
Requires-Dist: pydantic (>=2.0.0)
Project-URL: Homepage, https://github.com/leiuary/nonebot-plugin-mcserver-status-check
Project-URL: Repository, https://github.com/leiuary/nonebot-plugin-mcserver-status-check
